LICENSE
pwmled/__init__.py
pwmled/driver/__init__.py
pwmled/driver/gpio.py
pwmled/driver/pca9685.py
pwmled/led/__init__.py
pwmled/led/rgb.py
pwmled/led/rgbw.py
pwmled/transitions/__init__.py
pwmled/transitions/transition.py
pwmled/transitions/transition_manager.py
pwmled-1.6.11.dist-info/LICENSE
pwmled-1.6.11.dist-info/METADATA
pwmled-1.6.11.dist-info/WHEEL
pwmled-1.6.11.dist-info/RECORD
