Metadata-Version: 2.1
Name: pwmled
Version: 1.6.11
Summary: Control LEDs connected to a micro controller using pwm.
Home-page: https://github.com/soldag/python-pwmled
License: MIT
Keywords: pwm,light,gpio,pca9685
Author: soldag
Author-email: soren.oldag@gmail.com
Requires-Python: >=3.6,<4.0
Classifier: License :: OSI Approved :: MIT License
Classifier: Programming Language :: Python :: 3
Classifier: Programming Language :: Python :: 3.6
Classifier: Programming Language :: Python :: 3.7
Classifier: Programming Language :: Python :: 3.8
Classifier: Programming Language :: Python :: 3.9
Classifier: Programming Language :: Python :: 3.10
Classifier: Programming Language :: Python :: 3.11
Classifier: Topic :: Software Development :: Libraries :: Python Modules
Requires-Dist: adafruit-blinka (>=5.5.1,<9.0)
Requires-Dist: adafruit-circuitpython-pca9685 (>=3.3.2,<4.0)
Requires-Dist: pigpio (>=1.78,<2.0)
Requires-Dist: python-singleton (>=0.1.2,<1.0)
Project-URL: Repository, https://github.com/soldag/python-pwmled
